qspider/__init__.py
qspider/core.py
qspider/decorators.py
qspider/examples.py
qspider/utils.py
qspider/templates/process_template.py
qspider/templates/spider_template.py
qspider/templates/thread_template.py
test/__init__.py
qspider-0.1.6.dist-info/LICENSE
qspider-0.1.6.dist-info/METADATA
qspider-0.1.6.dist-info/WHEEL
qspider-0.1.6.dist-info/entry_points.txt
qspider-0.1.6.dist-info/top_level.txt
qspider-0.1.6.dist-info/RECORD
