Metadata-Version: 2.1
Name: qspider
Version: 0.1.6
Summary: An easy to use tools module for writing multi-thread and multi-process programs.
Home-page: UNKNOWN
Author: Tishacy
Author-email: 
License: UNKNOWN
Platform: UNKNOWN
Classifier: Programming Language :: Python :: 3
Classifier: Programming Language :: Python :: 3.5
Classifier: Programming Language :: Python :: 3.6
Classifier: Programming Language :: Python :: 3.7
Classifier: License :: OSI Approved :: MIT License
Classifier: Operating System :: OS Independent
Requires-Dist: termcolor (>=1.1.0)
Requires-Dist: requests (>=2.24.0)
Requires-Dist: colorama (>=0.4.4)
